<collection xmlns="http://exist.sourceforge.net/NS/exist" name="/db/apps/dashboard/resources/css" version="1" owner="admin" group="dba" mode="755" created="2016-02-15T14:52:19.352-05:00">
    <acl entries="0" version="1"/>
    <resource type="BinaryResource" name="Quicksand_Book-webfont.woff" skip="no" owner="admin" group="dba" mode="644" created="2016-02-15T14:52:19.379-05:00" modified="2016-02-15T14:52:19.379-05:00" filename="Quicksand_Book-webfont.woff" mimetype="application/font-woff">
        <acl entries="0" version="1"/>
    </resource>
    <resource type="BinaryResource" name="fonts.css" skip="no" owner="admin" group="dba" mode="644" created="2016-02-15T14:52:19.378-05:00" modified="2016-02-15T14:52:19.378-05:00" filename="fonts.css" mimetype="text/css">
        <acl entries="0" version="1"/>
    </resource>
    <resource type="BinaryResource" name="Quicksand_Book-webfont.eot" skip="no" owner="admin" group="dba" mode="644" created="2016-02-15T14:52:19.377-05:00" modified="2016-02-15T14:52:19.377-05:00" filename="Quicksand_Book-webfont.eot" mimetype="application/octet-stream">
        <acl entries="0" version="1"/>
    </resource>
    <resource type="BinaryResource" name="Quicksand_Book-webfont.ttf" skip="no" owner="admin" group="dba" mode="644" created="2016-02-15T14:52:19.377-05:00" modified="2016-02-15T14:52:19.377-05:00" filename="Quicksand_Book-webfont.ttf" mimetype="application/octet-stream">
        <acl entries="0" version="1"/>
    </resource>
    <resource type="BinaryResource" name="base.css" skip="no" owner="admin" group="dba" mode="644" created="2016-02-15T14:52:19.381-05:00" modified="2016-02-15T14:52:19.381-05:00" filename="base.css" mimetype="text/css">
        <acl entries="0" version="1"/>
    </resource>
    <resource type="BinaryResource" name="global.css" skip="no" owner="admin" group="dba" mode="644" created="2016-02-15T14:52:19.375-05:00" modified="2016-02-15T14:52:19.375-05:00" filename="global.css" mimetype="text/css">
        <acl entries="0" version="1"/>
    </resource>
    <resource type="XMLResource" name="Quicksand_Book-webfont.svg" skip="no" owner="admin" group="dba" mode="644" created="2016-02-15T14:52:19.352-05:00" modified="2016-02-15T14:52:19.352-05:00" filename="Quicksand_Book-webfont.svg" mimetype="image/svg+xml">
        <acl entries="0" version="1"/>
    </resource>
    <resource type="BinaryResource" name="base.less" skip="no" owner="admin" group="dba" mode="644" created="2016-02-15T14:52:19.376-05:00" modified="2016-02-15T14:52:19.376-05:00" filename="base.less" mimetype="application/less">
        <acl entries="0" version="1"/>
    </resource>
    <resource type="BinaryResource" name="global.less" skip="no" owner="admin" group="dba" mode="644" created="2016-02-15T14:52:19.38-05:00" modified="2016-02-15T14:52:19.38-05:00" filename="global.less" mimetype="application/less">
        <acl entries="0" version="1"/>
    </resource>
</collection>